inmanta_mitogen/__init__.py
inmanta_mitogen/py.typed
inmanta_plugins/mitogen/__init__.py
inmanta_plugins/mitogen/abc.py
inmanta_plugins/mitogen/py.typed
inmanta_plugins/mitogen/setup.cfg
inmanta_plugins/mitogen/files/.gitkeep
inmanta_plugins/mitogen/model/_init.cf
inmanta_plugins/mitogen/templates/.gitkeep
inmanta_module_mitogen-0.2.4.dist-info/METADATA
inmanta_module_mitogen-0.2.4.dist-info/WHEEL
inmanta_module_mitogen-0.2.4.dist-info/top_level.txt
inmanta_module_mitogen-0.2.4.dist-info/RECORD
