Metadata-Version: 2.4
Name: inmanta-module-mitogen
Version: 0.2.4
Author: Inmanta
Author-email: code@inmanta.com
License: ASL 2.0
Requires-Dist: inmanta-module-std
Requires-Dist: mitogen
